caterpyllar/__init__.py
caterpyllar/buffer.py
caterpyllar-0.0.3.dist-info/LICENSE
caterpyllar-0.0.3.dist-info/METADATA
caterpyllar-0.0.3.dist-info/WHEEL
caterpyllar-0.0.3.dist-info/top_level.txt
caterpyllar-0.0.3.dist-info/RECORD
