Metadata-Version: 2.1
Name: caterpyllar
Version: 0.0.3
Summary: A framework to work with DAGs of buffers.
Home-page: https://github.com/thorwhalen/newut/tree/master/caterpyllar
Author: Thor Whalen
License: mit
Platform: any
License-File: LICENSE
